pyupbit/__init__.py
pyupbit/errors.py
pyupbit/exchange_api.py
pyupbit/quotation_api.py
pyupbit/request_api.py
pyupbit/websocket_api.py
tests/__init__.py
tests/test_errors.py
tests/test_exchange_api.py
tests/test_quotation_api.py
tests/test_request_api.py
pyupbit-0.2.33.dist-info/LICENSE
pyupbit-0.2.33.dist-info/METADATA
pyupbit-0.2.33.dist-info/WHEEL
pyupbit-0.2.33.dist-info/top_level.txt
pyupbit-0.2.33.dist-info/RECORD
