Metadata-Version: 2.1
Name: pyupbit
Version: 0.2.33
Summary: python wrapper for Upbit API
Home-page: https://github.com/sharebook-kr/pyupbit
Author: Jonghun Yoo, Brayden Jo
Author-email: brayden.jo@outlook.com, jonghun.yoo@outlook.com, pyquant@outlook.com
License: UNKNOWN
Platform: UNKNOWN
Classifier: Programming Language :: Python :: 3
Classifier: License :: OSI Approved :: Apache Software License
Classifier: Operating System :: OS Independent
Requires-Python: >=3.6
License-File: LICENSE
